sensei/.DS_Store
sensei/__init__.py
sensei/_internal/__init__.py
sensei/_internal/_core/__init__.py
sensei/_internal/_core/_callable_handler.py
sensei/_internal/_core/_compat.py
sensei/_internal/_core/_endpoint.py
sensei/_internal/_core/_params.py
sensei/_internal/_core/_requester.py
sensei/_internal/_core/_route.py
sensei/_internal/_core/_types.py
sensei/_internal/_core/api_model.py
sensei/_internal/_core/args.py
sensei/_internal/_core/params_functions.py
sensei/_internal/_core/router.py
sensei/_internal/tools/__init__.py
sensei/_internal/tools/chained_map.py
sensei/_internal/tools/types.py
sensei/_internal/tools/utils.py
sensei/_utils.py
sensei/cases.py
sensei/client/__init__.py
sensei/client/exceptions.py
sensei/client/manager.py
sensei/client/rate_limiter.py
sensei/types.py
sensei-0.1.1.post3.dist-info/LICENSE
sensei-0.1.1.post3.dist-info/METADATA
sensei-0.1.1.post3.dist-info/WHEEL
sensei-0.1.1.post3.dist-info/RECORD
