Metadata-Version: 2.1
Name: sensei
Version: 0.1.1.post3
Summary: The Python framework that provides a quick way to build robust HTTP requests and best API clients. Use type hints, to build requests, with little or no implementation.
License: MIT
Keywords: api,client,api-client,api-wrapper,python-client,http-client,rest-api,pydantic,httpx,http-requests,requests
Author: Alexey 
Author-email: axbelenkov@gmail.com
Requires-Python: >=3.9,<4.0
Classifier: Development Status :: 4 - Beta
Classifier: Framework :: Pydantic
Classifier: Intended Audience :: Developers
Classifier: License :: OSI Approved :: MIT License
Classifier: Operating System :: OS Independent
Classifier: Programming Language :: Python :: 3
Classifier: Programming Language :: Python :: 3.9
Classifier: Programming Language :: Python :: 3.10
Classifier: Programming Language :: Python :: 3.11
Classifier: Programming Language :: Python :: 3.12
Classifier: Programming Language :: Python :: 3 :: Only
Classifier: Programming Language :: Python :: 3.13
Classifier: Topic :: Software Development :: Libraries :: Application Frameworks
Classifier: Topic :: Software Development :: Libraries :: Python Modules
Classifier: Typing :: Typed
Requires-Dist: httpcore (>=1.0.6,<2.0.0)
Requires-Dist: httpx (>=0.27.2,<0.28.0)
Requires-Dist: pydantic (>=2.9.2,<3.0.0)
Requires-Dist: typing-extensions (>=4.12.2,<5.0.0)
